MIPS/branch_predictor/Branch_predictor.vhd
library IEEE;
use IEEE.std_logic_1164.all;
use IEEE.numeric_std.all;

entity Branch_predictor is
    generic (
        SIZE      : integer := 32       -- Size of the branch history table (Index of the PC)
    );
    port (
        branch_ex       : in std_logic; 
        clock           : in std_logic;
        reset           : in std_logic; 
        pc_if           : in std_logic_vector(31 downto 0);
        pc_ex           : in std_logic_vector(31 downto 0);
        pc_cal          : in std_logic_vector(31 downto 0);
        pc_predict      : out std_logic_vector(31 downto 0);
        predict_if      : out std_logic;
        br_test         : out std_logic_vector(31 downto 0);
        predict_branch_test : out std_logic_vector(1 downto 0);
        tag_memory_table_test : out std_logic_vector(19 downto 0);
        valid_index_test : out std_logic
    );
end Branch_predictor;

architecture behavioral of Branch_predictor is

    -- Type declarations
    type pc_br is array(0 to SIZE-1) of std_logic_vector(31 downto 0);
    type prediction is array(0 to SIZE-1) of std_logic_vector(1 downto 0);
    type tag is array(0 to SIZE-1) of std_logic_vector(19 downto 0);
    type valid is array(0 to SIZE-1) of std_logic;

    -- Signal declarations
    signal br : pc_br;
    signal predict_branch : prediction;
    signal tag_memory_table : tag;
    signal valid_index : valid;

    alias tag_pc_if is pc_if(31 downto 12);
    alias index_if  is pc_if(12 downto 2);

    alias tag_pc_ex is pc_ex(31 downto 12);
    alias index_ex  is pc_ex(12 downto 2);

    signal new_predict_branch : prediction;
    signal writeEnable : std_logic_vector(SIZE-1 downto 0);
    signal taken : std_logic;
    signal incrementedPC : std_logic_vector(31 downto 0);

begin            

    -- Increment PC by 4 (for next instruction)
    incrementedPC <= std_logic_vector(unsigned(pc_if) + to_unsigned(4, 32));

    -- Process to write the history table when a branch or a jump is taken (with pc_ex)
    process(clock, reset)
    begin
        if reset = '1' then
            for i in 0 to SIZE-1 loop
                tag_memory_table(i) <= (others => '0');
                br(i) <= (others => '0');
                predict_branch(i) <= (others => '0');    -- Set all the predictions to not taken
                valid_index(i) <= '0';
            end loop;
        elsif rising_edge(clock) then 
            if branch_ex = '1' then 
                br(to_integer(unsigned(index_ex))) <= pc_cal;
                tag_memory_table(to_integer(unsigned(index_ex))) <= tag_pc_ex;
                predict_branch(to_integer(unsigned(index_ex))) <= new_predict_branch(to_integer(unsigned(index_ex)));
                valid_index(to_integer(unsigned(index_ex))) <= '1';

                -- Tests
                br_test <= br(to_integer(unsigned(index_ex)));
                tag_memory_table_test <= tag_memory_table(to_integer(unsigned(index_ex)));
                valid_index_test <= valid_index(to_integer(unsigned(index_ex)));
            end if;
        end if;
    end process;  



    -- Process to update prediction FSM
    process(clock)
    begin
        if rising_edge(clock) then
            if tag_memory_table(to_integer(unsigned(index_ex))) = tag_pc_ex then  -- Correspondence and update of dynamic branch prediction
                if branch_ex = '1' then
                    case predict_branch(to_integer(unsigned(index_ex))) is
                        when "11" =>
                            new_predict_branch(to_integer(unsigned(index_ex))) <= "11";  -- Strongly taken
                        when "10" =>
                            new_predict_branch(to_integer(unsigned(index_ex))) <= "11";  -- Taken
                        when "01" =>
                            new_predict_branch(to_integer(unsigned(index_ex))) <= "10";  -- Weakly taken
                        when others =>
                            new_predict_branch(to_integer(unsigned(index_ex))) <= "01";  -- Weakly not taken
                    end case;
                else
                    case predict_branch(to_integer(unsigned(index_ex))) is
                        when "11" =>
                            new_predict_branch(to_integer(unsigned(index_ex))) <= "10";  -- Weakly taken
                        when "10" =>
                            new_predict_branch(to_integer(unsigned(index_ex))) <= "01";  -- Weakly not taken
                        when "01" =>
                            new_predict_branch(to_integer(unsigned(index_ex))) <= "00";  -- Strongly not taken
                        when others =>
                            new_predict_branch(to_integer(unsigned(index_ex))) <= "00";  -- Strongly not taken
                    end case;
                end if;
            end if;
        end if;
    end process;

    -- Process to determine if the branch is taken or not
    process(index_if)
    begin
        case predict_branch(to_integer(unsigned(index_if))) is
            when "11" | "10" =>
                taken <= '1';  -- Branch taken
            when "01" | "00" =>
                taken <= '0';  -- Branch not taken
            when others =>
                taken <= '0';
        end case;
    end process;

    -- Predict the PC based on branch prediction or default incremented PC
    pc_predict <= br(to_integer(unsigned(index_if))) when taken = '1' 
                 and valid_index(to_integer(unsigned(index_if))) = '1'
                 and tag_memory_table(to_integer(unsigned(index_if))) = tag_pc_if
                 else incrementedPC;

    -- Output the prediction status
    predict_if <= taken;

end behavioral;

MIPS/branch_predictor/Branch_predictor_tb.vhd
library IEEE;
use IEEE.std_logic_1164.all;
use IEEE.numeric_std.all;

entity tb_Branch_predictor is
end tb_Branch_predictor;

architecture test of tb_Branch_predictor is
    -- Component declaration
    component Branch_predictor
        generic (
            SIZE : integer := 32
        );
        port (
            branch_ex   : in std_logic; 
            clock       : in std_logic;
            reset       : in std_logic; 
            pc_if       : in std_logic_vector(31 downto 0);
            pc_ex       : in std_logic_vector(31 downto 0);
            pc_cal      : in std_logic_vector(31 downto 0);
            pc_predict  : out std_logic_vector(31 downto 0);
            predict_if  : out std_logic;
            br_test     : out std_logic_vector(31 downto 0);
            tag_memory_table_test : out std_logic_vector(19 downto 0);
            valid_index_test : out std_logic
        );
    end component;

    -- Signals for connecting to the branch predictor
    signal branch_ex   : std_logic := '0';
    signal clock       : std_logic := '0';
    signal reset       : std_logic := '0';
    signal pc_if       : std_logic_vector(31 downto 0) := (others => '0');
    signal pc_ex       : std_logic_vector(31 downto 0) := (others => '0');
    signal pc_cal      : std_logic_vector(31 downto 0) := (others => '0');
    signal pc_predict  : std_logic_vector(31 downto 0);
    signal predict_if  : std_logic;
    signal br_test     : std_logic_vector(31 downto 0);
    signal tag_memory_table_test : std_logic_vector(19 downto 0);
    signal valid_index_test : std_logic;
    
    -- Clock period definition
    constant clk_period : time := 10 ns;

begin
    -- Instantiate the branch predictor
    uut: Branch_predictor
        port map (
            branch_ex   => branch_ex,
            clock       => clock,
            reset       => reset,
            pc_if       => pc_if,
            pc_ex       => pc_ex,
            pc_cal      => pc_cal,
            pc_predict  => pc_predict,
            predict_if  => predict_if,
            br_test     => br_test,
            tag_memory_table_test => tag_memory_table_test,
            valid_index_test => valid_index_test
        );

    -- Clock generation
    clock_process : process
    begin
        clock <= '0';
        wait for clk_period / 2;
        clock <= '1';
        wait for clk_period / 2;
    end process;

    -- Stimulus process to apply test cases
    stimulus: process
    begin
        -- Reset the predictor
        reset <= '1';
        wait for clk_period;
        reset <= '0';
        wait for clk_period * 2;  -- Pausa extra para estabilidade

        --  Test case 1: No branch taken initially
        -- ========================================
        pc_if <= x"00000000";
        pc_ex <= x"00000000";
        pc_cal <= x"00000010";  -- Next address if branch is taken (16 bytes ahead)
        branch_ex <= '0';        -- Branch not taken
        wait for clk_period * 2;

        report "Test case 1: No branch taken at pc_if = 0x00000000. Expected predict_if = '0'" severity note;
        assert predict_if = '0' report "Error: Expected no branch taken (predict_if = '0')." severity error;

        -- Test case 2
        -- ========================================
        pc_if <= x"00000000";
        pc_ex <= x"00000000";
        pc_cal <= x"00000020";  
        branch_ex <= '1';        -- Branch taken, store new address
        wait for clk_period * 2;

        report "Test case 2: Branch taken at pc_cal = 0x00000020. Expected predict_if = '0'" severity note;
        assert predict_if = '0' report "Error: Expected branch taken (predict_if = '0')." severity error;

        -- Test case 3
        -- ========================================
        pc_if <= x"00000000";
        pc_ex <= x"00000000";
        pc_cal <= x"00000030";  
        branch_ex <= '1';        -- Branch taken, store new address 10
        wait for clk_period * 2;

        report "Test case 3: No branch prediction at pc_if = 0x00000000. Expected predict_if = '0'" severity note;
        assert predict_if = '0' report "Error: Expected no branch taken (predict_if = '0')." severity error;

        -- Test case 4: Branch taken at a new address
        -- ========================================
        pc_if <= x"00000000";
        pc_ex <= x"00000000";
        pc_cal <= x"00000040";  
        branch_ex <= '1';
        wait for clk_period * 2;

        report "Test case 4: Branch taken at pc_ex = 0x00000000, pc_cal = 0x00000040. Expected predict_if = '1'" severity note;
        assert predict_if = '1' report "Error: Expected branch taken at new address (predict_if = '1')." severity error;

        wait;
    end process;
end test;

MIPS/branch_predictor/output.vcd
$date
  Thu Nov 14 15:10:41 2024
$end
$version
  GHDL v0
$end
$timescale
  1 fs
$end
$scope module standard $end
$upscope $end
$scope module std_logic_1164 $end
$upscope $end
$scope module numeric_std $end
$upscope $end
$scope module tb_branch_predictor $end
$var reg 1 ! branch_ex $end
$var reg 1 " clock $end
$var reg 1 # reset $end
$var reg 32 $ pc_if[31:0] $end
$var reg 32 % pc_ex[31:0] $end
$var reg 32 & pc_cal[31:0] $end
$var reg 32 ' pc_predict[31:0] $end
$var reg 1 ( predict_if $end
$var reg 32 ) br_test[31:0] $end
$var reg 20 * tag_memory_table_test[19:0] $end
$var reg 1 + valid_index_test $end
$scope module uut $end
$var reg 1 , branch_ex $end
$var reg 1 - clock $end
$var reg 1 . reset $end
$var reg 32 / pc_if[31:0] $end
$var reg 32 0 pc_ex[31:0] $end
$var reg 32 1 pc_cal[31:0] $end
$var reg 32 2 pc_predict[31:0] $end
$var reg 1 3 predict_if $end
$var reg 32 4 br_test[31:0] $end
$var reg 2 5 predict_branch_test[1:0] $end
$var reg 20 6 tag_memory_table_test[19:0] $end
$var reg 1 7 valid_index_test $end
$comment br is not handled $end
$comment predict_branch is not handled $end
$comment tag_memory_table is not handled $end
$var reg 32 8 valid_index[0:31] $end
$comment new_predict_branch is not handled $end
$var reg 32 9 writeenable[31:0] $end
$var reg 1 : taken $end
$var reg 32 ; incrementedpc[31:0] $end
$upscope $end
$upscope $end
$enddefinitions $end
#0
0!
0"
1#
b00000000000000000000000000000000 $
b00000000000000000000000000000000 %
b00000000000000000000000000000000 &
b00000000000000000000000000000100 '
0(
bUUUUUUUUUUUUUUUUUUUUUUUUUUUUUUUU )
bUUUUUUUUUUUUUUUUUUUU *
U+
0,
0-
1.
b00000000000000000000000000000000 /
b00000000000000000000000000000000 0
b00000000000000000000000000000000 1
b00000000000000000000000000000100 2
03
bUUUUUUUUUUUUUUUUUUUUUUUUUUUUUUUU 4
bUU 5
bUUUUUUUUUUUUUUUUUUUU 6
U7
b00000000000000000000000000000000 8
bUUUUUUUUUUUUUUUUUUUUUUUUUUUUUUUU 9
0:
b00000000000000000000000000000100 ;
#5000000
1"
1-
#10000000
0"
0#
0-
0.
#15000000
1"
1-
#20000000
0"
0-
#25000000
1"
1-
#30000000
0"
b00000000000000000000000000010000 &
0-
b00000000000000000000000000010000 1
#35000000
1"
1-
#40000000
0"
0-
#45000000
1"
1-
#50000000
1!
0"
b00000000000000000000000000100000 &
1,
0-
b00000000000000000000000000100000 1
#55000000
1"
b00000000000000000000000000000000 )
b00000000000000000000 *
0+
1-
b00000000000000000000000000000000 4
b00000000000000000000 6
07
b10000000000000000000000000000000 8
#60000000
0"
0-
#65000000
1"
b00000000000000000000000000100000 )
1+
1-
b00000000000000000000000000100000 4
17
#70000000
0"
b00000000000000000000000000110000 &
0-
b00000000000000000000000000110000 1
#75000000
1"
1-
#80000000
0"
0-
#85000000
1"
b00000000000000000000000000110000 )
1-
b00000000000000000000000000110000 4
#90000000
0"
b00000000000000000000000001000000 &
0-
b00000000000000000000000001000000 1
#95000000
1"
1-
#100000000
0"
0-
#105000000
1"
b00000000000000000000000001000000 )
1-
b00000000000000000000000001000000 4
